{".NET Framework 3.5":{"name":"ROSBridgeLib.geometry_msgs","assembly":"Assembly-CSharp","description":"","usedBy":[{"id":"ROSBridgeLib.auv_msgs","name":"ROSBridgeLib.auv_msgs"},{"id":"ROSBridgeLib.nav_msgs","name":"ROSBridgeLib.nav_msgs"}],"uses":[{"id":"ROSBridgeLib.std_msgs","name":"ROSBridgeLib.std_msgs"}],"types":[{"id":"ROSBridgeLib.geometry_msgs.PointMsg","kind":"class","accessibility":"public","name":"PointMsg","summary":""},{"id":"ROSBridgeLib.geometry_msgs.PoseMsg","kind":"class","accessibility":"public","name":"PoseMsg","summary":""},{"id":"ROSBridgeLib.geometry_msgs.PoseStampedMsg","kind":"class","accessibility":"public","name":"PoseStampedMsg","summary":""},{"id":"ROSBridgeLib.geometry_msgs.PoseWithCovarianceMsg","kind":"class","accessibility":"public","name":"PoseWithCovarianceMsg","summary":""},{"id":"ROSBridgeLib.geometry_msgs.QuaternionMsg","kind":"class","accessibility":"public","name":"QuaternionMsg","summary":""},{"id":"ROSBridgeLib.geometry_msgs.TwistMsg","kind":"class","accessibility":"public","name":"TwistMsg","summary":""},{"id":"ROSBridgeLib.geometry_msgs.TwistWithCovarianceMsg","kind":"class","accessibility":"public","name":"TwistWithCovarianceMsg","summary":""},{"id":"ROSBridgeLib.geometry_msgs.Vector3Msg","kind":"class","accessibility":"public","name":"Vector3Msg","summary":""}]}}