{".NET Framework 3.5":{"name":"SDK_SteamVRController","namespace":"VRTK","syntax":"public class SDK_SteamVRController : SDK_FallbackController","linkedSyntax":"public class [SDK_SteamVRController](#/type/VRTK.SDK_SteamVRController/index) : [SDK_FallbackController](#/type/VRTK.SDK_FallbackController/index)","baseTypes":[{"id":"VRTK.SDK_FallbackController","name":"VRTK.SDK_FallbackController"}],"summary":"<p>The SteamVR Controller SDK script provides a bridge to SDK methods that deal with the input devices.</p>"}}